doclink/__init__.py
doclink/__version__.py
doclink/builder.py
doclink/consumer.py
doclink/decorators.py
doclink/exceptions.py
doclink/meta_parser.py
doclink/request_meta.py
doclink/utils.py
doclink/arg/__init__.py
doclink/arg/groups.py
doclink/arg/models.py
doclink/clients/__init__.py
doclink/clients/requests_.py
doclink-1.1.0.dist-info/DESCRIPTION.rst
doclink-1.1.0.dist-info/LICENSE.txt
doclink-1.1.0.dist-info/METADATA
doclink-1.1.0.dist-info/RECORD
doclink-1.1.0.dist-info/WHEEL
doclink-1.1.0.dist-info/metadata.json
doclink-1.1.0.dist-info/top_level.txt
