Metadata-Version: 2.0
Name: doclink
Version: 1.1.0
Summary: Create HTTP client from pydoc
Home-page: UNKNOWN
Author: Yufu Luo
Author-email: fisherman.luo@gmail.com
License: MIT
Platform: UNKNOWN
Classifier: License :: OSI Approved :: MIT License
Classifier: Programming Language :: Python
Classifier: Programming Language :: Python :: 2.7
Classifier: Programming Language :: Python :: 3
Classifier: Programming Language :: Python :: 3.4
Classifier: Programming Language :: Python :: 3.5
Classifier: Programming Language :: Python :: 3.6
Classifier: Programming Language :: Python :: Implementation :: CPython
Requires-Dist: requests (>=2.18.0)
Requires-Dist: uritemplate (>=3.0.0)
Requires-Dist: pyyaml (>=3.12)
Requires-Dist: requests-toolbelt (>=0.8.0)
Requires-Dist: six (>=1.11.0)
